{
  "id": "61179dce-ac8b-4658-83ae-b7a163352dbb",
  "details": {
    "metadata_extended": {
      "body_type": "Athletic",
      "distinctive_features": [
        "Scars",
        "Short hair",
        "Dimples"
      ],
      "exercise_frequency": "Weekly",
      "diet_preferences": "Mediterranean",
      "sleep_schedule": "Early bird",
      "drugs_status": "Never",
      "drugs_use": [
        "None",
        "Caffeine"
      ],
      "social_media_usage": "Light",
      "communication_style": "Assertive",
      "humor_style": "Dry",
      "conflict_resolution": "Collaborative",
      "social_circle_size": "Medium",
      "childhood_location": "East London, England",
      "family_structure": "Nuclear",
      "trauma_history": "Experienced severe physical injury and existential shock following a major bus accident while traveling abroad, which necessitated physical rehabilitation and led to a profound shift in life priorities.",
      "income_range": "40k-60k",
      "career_stage": "Mid-career",
      "work_environment": "Restaurant",
      "job_satisfaction": "Satisfied",
      "career_ambitions": "Entrepreneurial",
      "myers_briggs_type": "INFJ",
      "emotional_intelligence": "High",
      "stress_response": [
        "Productive",
        "Rational",
        "Seeking support"
      ],
      "decision_making_style": [
        "Analytical",
        "Cautious"
      ],
      "learning_style": [
        "Reading/Writing",
        "Experiential"
      ],
      "core_values": [
        "Justice",
        "Integrity",
        "Growth",
        "Community",
        "Compassion"
      ],
      "moral_framework": [
        "Secular humanist",
        "Deontological",
        "Social contract"
      ],
      "environmental_consciousness": "High",
      "tech_savviness": "Proficient",
      "preferred_devices": [
        "Smartphone",
        "Laptop",
        "Smart watch"
      ],
      "news_consumption": "Heavy",
      "entertainment_preferences": [
        "Podcasts",
        "Documentaries",
        "Books",
        "Live events",
        "Museums"
      ],
      "attachment_style": "Secure",
      "relationship_history": [
        "Long-term relationships",
        "Currently partnered"
      ],
      "parental_status": "Wants children",
      "intimacy_comfort_level": "Moderate",
      "mental_health_status": "Good",
      "chronic_conditions": [
        "Allergies"
      ],
      "medication_usage": [
        "Vitamins/Supplements",
        "Prescription glasses/contacts"
      ],
      "therapy_experience": "Past",
      "housing_situation": "Rent",
      "transportation": [
        "Public transit",
        "Bike",
        "Walk"
      ],
      "travel_frequency": "Occasional",
      "spending_habits": "Frugal"
    }
  }
}