{
  "id": "8ccbb9f6-3710-42a9-a394-9912b6de7d13",
  "details": {
    "metadata_extended": {
      "body_type": "Athletic",
      "distinctive_features": [
        "Glasses",
        "Tattoos"
      ],
      "disabilities": [
        "None"
      ],
      "exercise_frequency": "Weekly",
      "diet_preferences": "Intermittent fasting",
      "sleep_schedule": "Night owl",
      "drugs_use": [
        "Alcohol",
        "Caffeine"
      ],
      "social_media_usage": "Light",
      "communication_style": "Direct",
      "social_circle_size": "Small",
      "childhood_location": "Atlanta, Georgia, USA",
      "family_structure": "Nuclear",
      "trauma_history": "Experienced social isolation and disconnect during schooling due to unconventional interests and blunt communication style, leading to a strong focus on self-reliance and intellectual pursuits.",
      "myers_briggs_type": "INTJ",
      "emotional_intelligence": "Average",
      "moral_framework": [
        "Secular humanist",
        "Utilitarian"
      ],
      "environmental_consciousness": "High",
      "tech_savviness": "Expert",
      "preferred_devices": [
        "Smartphone",
        "Laptop"
      ],
      "news_consumption": "Moderate",
      "entertainment_preferences": [
        "Books",
        "Documentaries",
        "Music"
      ],
      "attachment_style": "Avoidant",
      "parental_status": "Childfree by choice",
      "intimacy_comfort_level": "Private",
      "mental_health_status": "Good",
      "therapy_experience": "Open to it",
      "housing_situation": "Rent",
      "transportation": [
        "Car owner",
        "Walk"
      ],
      "travel_frequency": "Occasional",
      "spending_habits": "Value-seeking"
    }
  }
}