{
  "id": "2e7f68e0-4078-4b73-ab06-26a6019b9db0",
  "details": {
    "metadata_extended": {
      "body_type": "Average",
      "distinctive_features": [
        "Glasses",
        "Gray hair"
      ],
      "disabilities": [
        "None"
      ],
      "exercise_frequency": "Weekly",
      "diet_preferences": "Omnivore",
      "sleep_schedule": "Early bird",
      "drugs_use": [
        "Alcohol",
        "Caffeine"
      ],
      "social_media_usage": "Light",
      "communication_style": "Diplomatic",
      "social_circle_size": "Medium",
      "childhood_location": "Bristol, United Kingdom",
      "family_structure": "Nuclear",
      "trauma_history": "Experienced significant economic hardship during childhood recessions, leading to a deep-seated value of financial stability and order.",
      "myers_briggs_type": "INTJ",
      "emotional_intelligence": "High",
      "moral_framework": [
        "Pragmatic",
        "Social contract"
      ],
      "environmental_consciousness": "Moderate",
      "tech_savviness": "Proficient",
      "preferred_devices": [
        "Smartphone",
        "Laptop"
      ],
      "news_consumption": "Heavy",
      "entertainment_preferences": [
        "Streaming services",
        "Books",
        "Documentaries"
      ],
      "attachment_style": "Secure",
      "parental_status": "Has children",
      "intimacy_comfort_level": "Very open",
      "mental_health_status": "Good",
      "therapy_experience": "Past",
      "housing_situation": "Own",
      "transportation": [
        "Car owner",
        "Walk"
      ],
      "travel_frequency": "Occasional",
      "spending_habits": "Value-seeking"
    }
  }
}